spga/__init__.py
spga/core.py
spga/operators.py
spga/types.py
spga/utils.py
SPGA-0.1.3.dist-info/LICENSE
SPGA-0.1.3.dist-info/METADATA
SPGA-0.1.3.dist-info/WHEEL
SPGA-0.1.3.dist-info/top_level.txt
SPGA-0.1.3.dist-info/RECORD
